ldcpy/__init__.py
ldcpy/calcs.py
ldcpy/collect_datasets.py
ldcpy/comp_checker.py
ldcpy/derived_vars.py
ldcpy/plot.py
ldcpy/util.py
ldcpy-0.20.dist-info/licenses/LICENSE.txt
ldcpy-0.20.dist-info/METADATA
ldcpy-0.20.dist-info/WHEEL
ldcpy-0.20.dist-info/top_level.txt
ldcpy-0.20.dist-info/RECORD
