Metadata-Version: 2.4
Name: ldcpy
Version: 0.20
Summary: A library for lossy compression of netCDF files using xarray
Home-page: https://ldcpy.readthedocs.io
Maintainer: Alex Pinard
Maintainer-email: apinard@mines.edu
License: Apache 2.0
Project-URL: Documentation, https://ldcpy.readthedocs.io
Project-URL: Source, https://github.com/NCAR/ldcpy
Project-URL: Tracker, https://github.com/NCAR/ldcpy/issues
Keywords: compression,xarray
Classifier: Operating System :: OS Independent
Classifier: Intended Audience :: Science/Research
Classifier: Programming Language :: Python
Classifier: Programming Language :: Python :: 3
Classifier: Programming Language :: Python :: 3.10
Classifier: Topic :: Scientific/Engineering
Requires-Python: >=3.10
License-File: LICENSE.txt
Requires-Dist: cmocean
Requires-Dist: cartopy
Requires-Dist: dask[complete]
Requires-Dist: matplotlib
Requires-Dist: netcdf4
Requires-Dist: numpy
Requires-Dist: scikit-image
Requires-Dist: scipy
Requires-Dist: xarray
Requires-Dist: xrft
Requires-Dist: cf_xarray
Requires-Dist: cartopy
Requires-Dist: pandas
Requires-Dist: astropy
Requires-Dist: ipython
Requires-Dist: pooch
Requires-Dist: statsmodels
Dynamic: classifier
Dynamic: description
Dynamic: home-page
Dynamic: keywords
Dynamic: license
Dynamic: license-file
Dynamic: maintainer
Dynamic: maintainer-email
Dynamic: project-url
Dynamic: requires-dist
Dynamic: requires-python
Dynamic: summary
